{"1783497948439":[{"source":"diamond_block","exchangeRate":11.86},{"source":"netherite_ingot","exchangeRate":66.86},{"source":"minecraft:paper[custom_name={extra: [{bold: 1b, color: \"gray\", italic: 0b, obfuscated: 0b, strikethrough: 0b, text: \"Gräbergemisch\", underlined: 0b}], text: \"\"},custom_model_data={floats: [626.0f]},item_name={extra: [{bold: 1b, color: \"gray\", italic: 0b, obfuscated: 0b, strikethrough: 0b, text: \"Gräbergemisch\", underlined: 0b}], text: \"\"}]","exchangeRate":13.7},{"source":"minecraft:paper[custom_name={extra: [{bold: 1b, color: \"#926428\", italic: 0b, obfuscated: 0b, strikethrough: 0b, text: \"Holzbündel\", underlined: 0b}], text: \"\"},custom_model_data={floats: [625.0f]},item_name={extra: [{bold: 1b, color: \"#926428\", italic: 0b, obfuscated: 0b, strikethrough: 0b, text: \"Holzbündel\", underlined: 0b}], text: \"\"}]","exchangeRate":18.52},{"source":"minecraft:paper[custom_name={extra: [{bold: 1b, color: \"white\", italic: 0b, obfuscated: 0b, strikethrough: 0b, text: \"Steinplatten\", underlined: 0b}], text: \"\"},custom_model_data={floats: [635.0f]},item_name={extra: [{bold: 1b, color: \"white\", italic: 0b, obfuscated: 0b, strikethrough: 0b, text: \"Steinplatten\", underlined: 0b}], text: \"\"}]","exchangeRate":13.49}]}